kvutil/__init__.py
kvutil/kv.py
kvutil-1.0.3.dist-info/LICENSE
kvutil-1.0.3.dist-info/METADATA
kvutil-1.0.3.dist-info/WHEEL
kvutil-1.0.3.dist-info/entry_points.txt
kvutil-1.0.3.dist-info/top_level.txt
kvutil-1.0.3.dist-info/RECORD
