Metadata-Version: 2.1
Name: kvutil
Version: 1.0.3
Summary: Comand-line key-value store
Home-page: https://github.com/mhv2109/kvutil
Author: mhv2109
License: UNKNOWN
Platform: UNKNOWN
Classifier: Programming Language :: Python :: 3.5
Classifier: Programming Language :: Python :: 3.6
Classifier: Programming Language :: Python :: 3.7
Classifier: License :: OSI Approved :: MIT License
Classifier: Operating System :: OS Independent
